hypercli/__init__.py
hypercli/billing.py
hypercli/client.py
hypercli/config.py
hypercli/files.py
hypercli/http.py
hypercli/instances.py
hypercli/jobs.py
hypercli/logs.py
hypercli/renders.py
hypercli/user.py
hypercli/job/__init__.py
hypercli/job/base.py
hypercli/job/comfyui.py
hypercli_sdk-0.4.7.dist-info/METADATA
hypercli_sdk-0.4.7.dist-info/WHEEL
hypercli_sdk-0.4.7.dist-info/RECORD
