Metadata-Version: 2.4
Name: hypercli-sdk
Version: 0.4.7
Summary: Python SDK for HyperCLI - GPU orchestration and LLM API
Project-URL: Homepage, https://hypercli.com
Project-URL: Documentation, https://docs.hypercli.com
Project-URL: Repository, https://github.com/HyperCLI/hypercli
Author-email: HyperCLI <support@hypercli.com>
License-Expression: MIT
Classifier: Development Status :: 4 - Beta
Classifier: Intended Audience :: Developers
Classifier: License :: OSI Approved :: MIT License
Classifier: Programming Language :: Python :: 3.10
Classifier: Programming Language :: Python :: 3.11
Classifier: Programming Language :: Python :: 3.12
Requires-Python: >=3.10
Requires-Dist: httpx>=0.28.1
Requires-Dist: websockets>=15.0.1
Provides-Extra: comfyui
Requires-Dist: comfyui-workflow-templates-media-image>=0.3.0; extra == 'comfyui'
Requires-Dist: comfyui-workflow-templates>=0.7.0; extra == 'comfyui'
Provides-Extra: dev
Requires-Dist: pytest-asyncio>=0.23.0; extra == 'dev'
Requires-Dist: pytest>=8.0.0; extra == 'dev'
Requires-Dist: ruff>=0.3.0; extra == 'dev'
